jtextprocessor/__init__.py
jtextprocessor/jconverter.py
jtextprocessor/mecab_handler.py
jtextprocessor/processor.py
jtextprocessor/replacer.py
jtextprocessor/data/stopwords.utf8
kotonoha/__init__.py
kotonoha/jconverter.py
kotonoha/kotonoha.py
kotonoha/mecab_handler.py
kotonoha/replacer.py
kotonoha/data/stopwords.utf8
kotonoha-0.4.1.dist-info/AUTHORS.rst
kotonoha-0.4.1.dist-info/LICENSE
kotonoha-0.4.1.dist-info/METADATA
kotonoha-0.4.1.dist-info/WHEEL
kotonoha-0.4.1.dist-info/top_level.txt
kotonoha-0.4.1.dist-info/RECORD
