Metadata-Version: 2.1
Name: kotonoha
Version: 0.4.1
Summary: Tools for preprocessing Japanese texts
Home-page: https://github.com/brunotoshio/kotonoha
Author: Bruno Toshio Sugano
Author-email: brunotoshio@gmail.com
License: MIT license
Project-URL: Documentation, https://kotonoha.readthedocs.io/
Project-URL: Changelog, https://kotonoha.readthedocs.io/en/latest/changelog.html
Project-URL: Issue Tracker, https://github.com/brunotoshio/kotonoha/issues
Keywords: japanese,textprocessing,nlp
Platform: UNKNOWN
Classifier: Intended Audience :: Developers
Classifier: License :: OSI Approved :: MIT License
Classifier: Operating System :: Unix
Classifier: Operating System :: POSIX
Classifier: Operating System :: Microsoft :: Windows
Classifier: Programming Language :: Python
Classifier: Programming Language :: Python :: 3.6
Classifier: Topic :: Utilities
Requires-Python: ~=3.6
Requires-Dist: jaconv (==0.2.4)
